bron/__init__.py
bron/__main__.py
bron/cli.py
bron/config.py
bron/exceptions.py
bron/render.py
bron/logic/__init__.py
bron/logic/checker.py
bron/logic/dependencies.py
bron/logic/erase.py
bron/logic/locate.py
bron/logic/merge.py
bron/logic/resolve.py
bron/logic/update.py
bron/procedures/__init__.py
bron/procedures/add.py
bron/procedures/bootstrap.py
bron/procedures/format.py
bron/procedures/list.py
bron/procedures/purge.py
bron/procedures/remove.py
bron/procedures/sync.py
bron-0.2.0.dist-info/METADATA
bron-0.2.0.dist-info/WHEEL
bron-0.2.0.dist-info/entry_points.txt
bron-0.2.0.dist-info/licenses/LICENSE.md
bron-0.2.0.dist-info/RECORD
